setup.py
flip_dsnd_probability/Binomialdistribution.py
flip_dsnd_probability/Gaussiandistribution.py
flip_dsnd_probability/Generaldistribution.py
flip_dsnd_probability/__init__.py
flip_dsnd_probability.egg-info/PKG-INFO
flip_dsnd_probability.egg-info/SOURCES.txt
flip_dsnd_probability.egg-info/dependency_links.txt
flip_dsnd_probability.egg-info/not-zip-safe
flip_dsnd_probability.egg-info/top_level.txt