Metadata-Version: 1.0
Name: flip-dsnd-probability
Version: 0.1
Summary: Gaussian and Binomial distributions
Home-page: UNKNOWN
Author: Felipe Gonçalves
Author-email: UNKNOWN
License: UNKNOWN
Platform: UNKNOWN
